pyplant/__init__.py
pyplant/pyplant.py
pyplant/specs.py
pyplant/utils.py
pyplant/test/PipeworkMock.py
pyplant/test/__init__.py
pyplant/test/test_utils.py
pyplant-0.6.0.dist-info/LICENSE.txt
pyplant-0.6.0.dist-info/METADATA
pyplant-0.6.0.dist-info/WHEEL
pyplant-0.6.0.dist-info/top_level.txt
pyplant-0.6.0.dist-info/RECORD
